dapl_secure_bucket/__init__.py
dapl_secure_bucket/py.typed
dapl_secure_bucket/_jsii/__init__.py
dapl_secure_bucket/_jsii/dapl_secure_bucket@0.0.3.jsii.tgz
dapl_secure_bucket-0.0.3.dist-info/LICENSE
dapl_secure_bucket-0.0.3.dist-info/METADATA
dapl_secure_bucket-0.0.3.dist-info/WHEEL
dapl_secure_bucket-0.0.3.dist-info/top_level.txt
dapl_secure_bucket-0.0.3.dist-info/RECORD
